[
    {
        "Category": "Management & Governance",
        "Title": "AWS Systems Manager Automation now supports targeting all instances in the account and Region",
        "Date": "20/12/2019",
        "Link": "https://aws.amazon.com/about-aws/whats-new/2019/12/aws-systems-manager-automation-now-supports-targeting-all-instances-in-the-account-and-region/",
        "Services": [
            "AWS Systems Manager"
        ]
    },
    {
        "Category": "Management & Governance",
        "Title": "AWS Systems Manager Automation now supports adding tags to your executions",
        "Date": "20/12/2019",
        "Link": "https://aws.amazon.com/about-aws/whats-new/2019/12/aws-systems-manager-automation-now-supports-adding-tags-to-your-executions/",
        "Services": [
            "AWS Systems Manager"
        ]
    },
    {
        "Category": "Management & Governance",
        "Title": "AWS Systems Manager Automation now supports running a single workflow in remote accounts and Regions",
        "Date": "20/12/2019",
        "Link": "https://aws.amazon.com/about-aws/whats-new/2019/12/aws-systems-manager-automation-now-supports-running-a-single-workflow-in-remote-accounts-and-regions/",
        "Services": [
            "AWS Systems Manager"
        ]
    },
    {
        "Category": "Management & Governance",
        "Title": "AWS OpsWorks for Configuration Management now supports tagging and tag-based access control",
        "Date": "19/12/2019",
        "Link": "https://aws.amazon.com/about-aws/whats-new/2019/12/aws-opsworks-cm-supports-tagging-tag-based-access-control/",
        "Services": [
            "AWS OpsWorks"
        ]
    },
    {
        "Category": "Management & Governance",
        "Title": "Session Manager now available directly from the Amazon EC2 console",
        "Date": "19/12/2019",
        "Link": "https://aws.amazon.com/about-aws/whats-new/2019/12/session-manager-now-available-directly-from-amazon-ec2-console/",
        "Services": [
            "Amazon EC2"
        ]
    },
    {
        "Category": "Management & Governance",
        "Title": "AWS Service Catalog supports deprecation of product versions",
        "Date": "18/12/2019",
        "Link": "https://aws.amazon.com/about-aws/whats-new/2019/12/aws-service-catalog-supports-deprecation-product-versions/",
        "Services": [
            "Service Catalog"
        ]
    },
    {
        "Category": "Management & Governance",
        "Title": "AWS CloudFormation updates for Amazon API Gateway, AWS CodePipeline, Amazon S3, AWS IAM, Amazon ECS, Amazon RDS, Amazon ES, AWS Lambda and more",
        "Date": "17/12/2019",
        "Link": "https://aws.amazon.com/about-aws/whats-new/2019/12/aws-cloudformation-updates-for-api-gateway-codepipeline-s3-iam-ecs-rds-es-lambda-and-more/",
        "Services": [
            "Amazon S3",
            "AWS CloudFormation",
            "AWS Lambda",
            "Amazon API Gateway",
            "AWS CodePipeline"
        ]
    },
    {
        "Category": "Management & Governance",
        "Title": "Amazon EC2 Spot Now Provides Instance Launch Notifications via Amazon CloudWatch Events",
        "Date": "13/12/2019",
        "Link": "https://aws.amazon.com/about-aws/whats-new/2019/12/amazon-ec2-spot-now-provides-instance-launch-notifications-via-amazon-cloudwatch-events/",
        "Services": [
            "Amazon EC2",
            "Amazon CloudWatch"
        ]
    },
    {
        "Category": "Management & Governance",
        "Title": "The AWS Well-Architected Tool is now available in the Europe (Frankfurt) Region",
        "Date": "11/12/2019",
        "Link": "https://aws.amazon.com/about-aws/whats-new/2019/12/aws-well-architected-tool-available-in-europe-frankfurt-region/",
        "Services": [
            "AWS Well-Architected Tool"
        ]
    },
    {
        "Category": "Management & Governance",
        "Title": "Introducing The Amazon Builders\u2019 Library",
        "Date": "05/12/2019",
        "Link": "https://aws.amazon.com/about-aws/whats-new/2019/12/introducing-amazon-builders-library/",
        "Services": []
    },
    {
        "Category": "Management & Governance",
        "Title": "Amazon ECS Cluster Auto Scaling Now Available",
        "Date": "03/12/2019",
        "Link": "https://aws.amazon.com/about-aws/whats-new/2019/12/amazon-ecs-cluster-auto-scaling-now-available/",
        "Services": []
    },
    {
        "Category": "Management & Governance",
        "Title": "AWS License Manager now adds Dedicated Host management capabilities to simplify your \u2018Bring your own license\u2019 (BYOL) experience",
        "Date": "02/12/2019",
        "Link": "https://aws.amazon.com/about-aws/whats-new/2019/12/aws-license-manager-adds-dedicated-host-management-capabilities/",
        "Services": [
            "AWS License Manager"
        ]
    },
    {
        "Category": "Management & Governance",
        "Title": "AWS License Manager allows administrators to automate discovery of existing software licenses",
        "Date": "02/12/2019",
        "Link": "https://aws.amazon.com/about-aws/whats-new/2019/12/aws-license-manager-allows-administrators-to-automate-discovery-of-existing-software-licenses/",
        "Services": [
            "AWS License Manager"
        ]
    },
    {
        "Category": "Management & Governance",
        "Title": "Manage access to AWS centrally for Azure AD users with AWS Single Sign-on",
        "Date": "27/11/2019",
        "Link": "https://aws.amazon.com/about-aws/whats-new/2019/11/manage-access-to-aws-centrally-for-azure-ad-users-with-aws-single-sign-on/",
        "Services": []
    },
    {
        "Category": "Management & Governance",
        "Title": "AWS Managed Services (AMS) now supports AWS CloudFormation Stack Update",
        "Date": "27/11/2019",
        "Link": "https://aws.amazon.com/about-aws/whats-new/2019/11/aws-managed-services-ams-now-supports-aws-cloudformation-stack-update/",
        "Services": [
            "AWS CloudFormation"
        ]
    },
    {
        "Category": "Management & Governance",
        "Title": "Access your AWS Regions faster using the AWS Management Console",
        "Date": "27/11/2019",
        "Link": "https://aws.amazon.com/about-aws/whats-new/2019/11/faster-access-to-regions-on-AWS-management-console/",
        "Services": []
    },
    {
        "Category": "Management & Governance",
        "Title": "AWS Managed Services (AMS) now supports Windows 2019",
        "Date": "26/11/2019",
        "Link": "https://aws.amazon.com/about-aws/whats-new/2019/11/aws-managed-services-ams-now-supports-windows-2019/",
        "Services": []
    },
    {
        "Category": "Management & Governance",
        "Title": "CloudWatch Application Insights for .NET and SQL Server now supports Windows Performance Counters, SQL Server on Linux, and more",
        "Date": "26/11/2019",
        "Link": "https://aws.amazon.com/about-aws/whats-new/2019/11/amazon-cloudwatch-application-insights-net-sql-server-support-windows-performance-counters/",
        "Services": []
    },
    {
        "Category": "Management & Governance",
        "Title": "Amazon CloudWatch Now Includes Contributor Insights - in Preview",
        "Date": "26/11/2019",
        "Link": "https://aws.amazon.com/about-aws/whats-new/2019/11/amazon-cloudwatch-now-includes-contributor-insights-preview/",
        "Services": [
            "Amazon CloudWatch"
        ]
    },
    {
        "Category": "Management & Governance",
        "Title": "Simplify application configuration with AWS AppConfig",
        "Date": "26/11/2019",
        "Link": "https://aws.amazon.com/about-aws/whats-new/2019/11/simplify-application-configuration-with-aws-appconfig/",
        "Services": []
    },
    {
        "Category": "Management & Governance",
        "Title": "Introducing Amazon CloudWatch Synthetics - Now in Preview",
        "Date": "26/11/2019",
        "Link": "https://aws.amazon.com/about-aws/whats-new/2019/11/introducing-amazon-cloudwatch-synthetics-preview/",
        "Services": [
            "Amazon CloudWatch"
        ]
    },
    {
        "Category": "Management & Governance",
        "Title": "Grafana Labs and AWS add optimizations and new features to Amazon CloudWatch data source",
        "Date": "25/11/2019",
        "Link": "https://aws.amazon.com/about-aws/whats-new/2019/11/grafana-labs-aws-add-optimizations-new-features-amazon-cloudwatch-data-source/",
        "Services": [
            "Amazon CloudWatch"
        ]
    },
    {
        "Category": "Management & Governance",
        "Title": "AWS Service Catalog adds High Reliability Architectures to the Getting Started Library",
        "Date": "25/11/2019",
        "Link": "https://aws.amazon.com/about-aws/whats-new/2019/11/aws-service-catalog-adds-high-reliability-architectures-getting-started-library/",
        "Services": [
            "Service Catalog"
        ]
    },
    {
        "Category": "Management & Governance",
        "Title": "Simplify cloud provisioning with AWS Service Catalog Connector for Jira Service Desk",
        "Date": "23/11/2019",
        "Link": "https://aws.amazon.com/about-aws/whats-new/2019/11/simplify-cloud-provisioning-with-aws-service-catalog-connector-for-jira-service-desk/",
        "Services": [
            "Service Catalog"
        ]
    },
    {
        "Category": "Management & Governance",
        "Title": "AWS CloudTrail announces CloudTrail Insights",
        "Date": "22/11/2019",
        "Link": "https://aws.amazon.com/about-aws/whats-new/2019/11/aws-cloudtrail-announces-cloudtrail-insights/",
        "Services": [
            "AWS CloudTrail"
        ]
    },
    {
        "Category": "Management & Governance",
        "Title": "Amazon CloudWatch Logs Insights is now available in the Europe (Stockholm) AWS Region",
        "Date": "22/11/2019",
        "Link": "https://aws.amazon.com/about-aws/whats-new/2019/11/amazon-cloudwatch-logs-insights-now-available-in-europe-stockholm-region/",
        "Services": [
            "Amazon CloudWatch"
        ]
    },
    {
        "Category": "Management & Governance",
        "Title": "Use IAM to share your AWS resources with groups of AWS accounts in AWS Organizations",
        "Date": "21/11/2019",
        "Link": "https://aws.amazon.com/about-aws/whats-new/2019/11/use-iam-share-aws-resources-with-groups-aws-accounts-aws-organizations/",
        "Services": [
            "AWS Organizations"
        ]
    },
    {
        "Category": "Management & Governance",
        "Title": "Introducing AWS Systems Manager Explorer",
        "Date": "20/11/2019",
        "Link": "https://aws.amazon.com/about-aws/whats-new/2019/11/introducing-aws-systems-manager-explorer/",
        "Services": [
            "AWS Systems Manager"
        ]
    },
    {
        "Category": "Management & Governance",
        "Title": "ECS container instances monitoring now available in Amazon CloudWatch Container Insights",
        "Date": "20/11/2019",
        "Link": "https://aws.amazon.com/about-aws/whats-new/2019/11/ecs-container-instances-monitoring-now-available-in-amazon-cloudwatch-container-insights/",
        "Services": [
            "Amazon CloudWatch"
        ]
    },
    {
        "Category": "Management & Governance",
        "Title": "New AWS Service Catalog Connector for ServiceNow supports Budgets integration and FIPS endpoints",
        "Date": "19/11/2019",
        "Link": "https://aws.amazon.com/about-aws/whats-new/2019/11/new-aws-service-catalog-connector-for-servicenow-supports-budgets-integration-and-fips-endpoints/",
        "Services": [
            "Service Catalog"
        ]
    },
    {
        "Category": "Management & Governance",
        "Title": "CloudFormation Announces Drift Detection Support in StackSets",
        "Date": "19/11/2019",
        "Link": "https://aws.amazon.com/about-aws/whats-new/2019/11/cloudformation-announces-drift-detection-support-in-stackSets/",
        "Services": []
    },
    {
        "Category": "Management & Governance",
        "Title": "Amazon CloudWatch Launches Usage Metrics and Service Quotas Integration",
        "Date": "19/11/2019",
        "Link": "https://aws.amazon.com/about-aws/whats-new/2019/11/amazon-cloudwatch-adds-service-usage-metrics-integration-service-quotas/",
        "Services": [
            "Amazon CloudWatch"
        ]
    },
    {
        "Category": "Management & Governance",
        "Title": "Amazon CloudWatch Launches Embedded Metric Format",
        "Date": "19/11/2019",
        "Link": "https://aws.amazon.com/about-aws/whats-new/2019/11/amazon-cloudwatch-launches-embedded-metric-format/",
        "Services": [
            "Amazon CloudWatch"
        ]
    },
    {
        "Category": "Management & Governance",
        "Title": "AWS Managed Services (AMS) now supports SUSE Linux Enterprise Server 12 SP4",
        "Date": "16/11/2019",
        "Link": "https://aws.amazon.com/about-aws/whats-new/2019/11/aws-managed-services-now-supports-suse-linux-enterprise-server-12-sp4/",
        "Services": []
    },
    {
        "Category": "Management & Governance",
        "Title": "Parameter Store announces enhanced search experience",
        "Date": "16/11/2019",
        "Link": "https://aws.amazon.com/about-aws/whats-new/2019/11/parameter-store-announces-enhanced-search-experience/",
        "Services": []
    },
    {
        "Category": "Management & Governance",
        "Title": "Automate your operational playbooks with AWS Systems Manager",
        "Date": "15/11/2019",
        "Link": "https://aws.amazon.com/about-aws/whats-new/2019/11/automate-your-operational-playbooks-with-aws-systems-manager/",
        "Services": [
            "AWS Systems Manager"
        ]
    },
    {
        "Category": "Management & Governance",
        "Title": "Easily deploy SQL Server Always On solutions using the AWS Launch Wizard for SQL Server",
        "Date": "14/11/2019",
        "Link": "https://aws.amazon.com/about-aws/whats-new/2019/11/easily-deploy-sql-server-always-on-solutions-using-aws-launch-wizard/",
        "Services": [
            "AWS Launch Wizard"
        ]
    },
    {
        "Category": "Management & Governance",
        "Title": "AWS CloudFormation Launches Resource Import",
        "Date": "13/11/2019",
        "Link": "https://aws.amazon.com/about-aws/whats-new/2019/11/aws-cloudformation-launches-resource-import/",
        "Services": [
            "AWS CloudFormation"
        ]
    },
    {
        "Category": "Management & Governance",
        "Title": "Amazon CloudWatch Metric Math now supports additional functions",
        "Date": "13/11/2019",
        "Link": "https://aws.amazon.com/about-aws/whats-new/2019/11/amazon-cloudwatch-metric-math-now-supports-additional-functions/",
        "Services": [
            "Amazon CloudWatch"
        ]
    },
    {
        "Category": "Management & Governance",
        "Title": "Use the AWS CLI v2 preview with AWS Single Sign-on to increase developer productivity",
        "Date": "11/11/2019",
        "Link": "https://aws.amazon.com/about-aws/whats-new/2019/11/use-the-aws-cli-v2-preview-with-aws-single-sign-on-to-increase-developer-productivity/",
        "Services": []
    },
    {
        "Category": "Management & Governance",
        "Title": "Amazon CloudWatch launches cross-account cross-region dashboards",
        "Date": "09/11/2019",
        "Link": "https://aws.amazon.com/about-aws/whats-new/2019/11/amazon-cloudwatch-launches-cross-account-cross-region-dashboards/",
        "Services": [
            "Amazon CloudWatch"
        ]
    },
    {
        "Category": "Management & Governance",
        "Title": "Now use single-click setup to keep AWS Systems Manager Agents automatically updated",
        "Date": "06/11/2019",
        "Link": "https://aws.amazon.com/about-aws/whats-new/2019/11/use-single-click-setup-aws-systems-manager-agents-automatically-updated/",
        "Services": [
            "AWS Systems Manager"
        ]
    },
    {
        "Category": "Management & Governance",
        "Title": "AWS Service Catalog enables transfer of provisioned product ownership",
        "Date": "01/11/2019",
        "Link": "https://aws.amazon.com/about-aws/whats-new/2019/10/aws-service-catalog-enables-transfer-of-provisioned-product-ownership/",
        "Services": [
            "Service Catalog"
        ]
    },
    {
        "Category": "Management & Governance",
        "Title": "AWS License Manager now helps you easily identify Windows and SQL Server License Included instances",
        "Date": "26/10/2019",
        "Link": "https://aws.amazon.com/about-aws/whats-new/2019/10/aws-license-manager-now-helps-easily-identify-windows-and-sql-server-license-included-instances/",
        "Services": [
            "AWS License Manager"
        ]
    },
    {
        "Category": "Management & Governance",
        "Title": "AWS Managed Services (AMS) Now Offers Managed Landing Zones",
        "Date": "25/10/2019",
        "Link": "https://aws.amazon.com/about-aws/whats-new/2019/10/aws-managed-services-now-offers-managed-landing-zones/",
        "Services": []
    },
    {
        "Category": "Management & Governance",
        "Title": "AWS Managed Services adds support for 29 additional AWS Services",
        "Date": "24/10/2019",
        "Link": "https://aws.amazon.com/about-aws/whats-new/2019/10/aws-managed-services-adds-support-29-additional-aws-services/",
        "Services": []
    },
    {
        "Category": "Management & Governance",
        "Title": "AWS Managed Services (AMS) Adds Developer Mode to Accelerate Migrations",
        "Date": "24/10/2019",
        "Link": "https://aws.amazon.com/about-aws/whats-new/2019/10/aws-managed-services-adds-developer-mode-accelerate-migrations/",
        "Services": []
    },
    {
        "Category": "Management & Governance",
        "Title": "AWS IoT Things Graph now provides workflow monitoring with AWS CloudWatch",
        "Date": "19/10/2019",
        "Link": "https://aws.amazon.com/about-aws/whats-new/2019/10/aws-iot-things-graph-now-provides-workflow-monitoring-with-aws-cloudwatch/",
        "Services": []
    },
    {
        "Category": "Management & Governance",
        "Title": "Amazon CloudWatch now sends alarm state change events to Amazon EventBridge",
        "Date": "18/10/2019",
        "Link": "https://aws.amazon.com/about-aws/whats-new/2019/10/amazon-cloudwatch-sends-alarm-state-change-events-amazon-eventbridge/",
        "Services": [
            "Amazon EventBridge",
            "Amazon CloudWatch"
        ]
    },
    {
        "Category": "Management & Governance",
        "Title": "Amazon CloudWatch Anomaly Detection is now available in all commercial AWS regions",
        "Date": "18/10/2019",
        "Link": "https://aws.amazon.com/about-aws/whats-new/2019/10/amazon-cloudwatch-anomaly-detection-now-generally-available/",
        "Services": [
            "Amazon CloudWatch"
        ]
    },
    {
        "Category": "Management & Governance",
        "Title": "AWS Resource Groups and Tag Editor Are Now Available in the AWS GovCloud (US) Regions",
        "Date": "15/10/2019",
        "Link": "https://aws.amazon.com/about-aws/whats-new/2019/10/aws-resource-groups-and-tag-editor-are-now-available-in-the-aws-govcloud-us-regions/",
        "Services": []
    },
    {
        "Category": "Management & Governance",
        "Title": "AWS Chatbot Now Supports Notifications from AWS Config",
        "Date": "11/10/2019",
        "Link": "https://aws.amazon.com/about-aws/whats-new/2019/10/aws-chatbot-now-supports-notifications-from-aws-config/",
        "Services": [
            "AWS Chatbot",
            "AWS Config"
        ]
    },
    {
        "Category": "Management & Governance",
        "Title": "AWS Managed Services Console now supports search and usage-based filtering to improve change type discovery",
        "Date": "08/10/2019",
        "Link": "https://aws.amazon.com/about-aws/whats-new/2019/10/aws-managed-services-console-now-supports-search-and-usage-based-filtering-to-improve-change-type-discovery/",
        "Services": []
    },
    {
        "Category": "Management & Governance",
        "Title": "Amazon VPC Traffic Mirroring Now Supports AWS CloudFormation",
        "Date": "08/10/2019",
        "Link": "https://aws.amazon.com/about-aws/whats-new/2019/10/amazon-vpc-traffic-mirroring-now-supports-aws-cloudformation/",
        "Services": [
            "AWS CloudFormation",
            "Amazon VPC"
        ]
    },
    {
        "Category": "Management & Governance",
        "Title": "AWS Well-Architected Tool now available in the Asia Pacific (Tokyo) Region and localized into Japanese",
        "Date": "26/09/2019",
        "Link": "https://aws.amazon.com/about-aws/whats-new/2019/09/aws-well-architected-tool-now-available-tokyo-region-and-localized-into-japanese/",
        "Services": [
            "AWS Well-Architected Tool"
        ]
    },
    {
        "Category": "Management & Governance",
        "Title": "AWS CloudFormation updates for Amazon EC2, Amazon ECS, Amazon ElastiCache, Amazon ElasticSearch, and more",
        "Date": "20/09/2019",
        "Link": "https://aws.amazon.com/about-aws/whats-new/2019/09/aws-cloudformation-updates-amazon-ec2-ecs-elasticache-elasticsearch/",
        "Services": [
            "Amazon ElastiCache",
            "Amazon EC2",
            "AWS CloudFormation"
        ]
    },
    {
        "Category": "Management & Governance",
        "Title": "AWS Service Catalog Announces Budget Visibility",
        "Date": "12/09/2019",
        "Link": "https://aws.amazon.com/about-aws/whats-new/2019/09/service-catalog-announces-budget-visibility/",
        "Services": [
            "Service Catalog"
        ]
    },
    {
        "Category": "Management & Governance",
        "Title": "AWS Systems Manager Automation now supports additional queuing",
        "Date": "05/09/2019",
        "Link": "https://aws.amazon.com/about-aws/whats-new/2019/09/aws-systems-manager-automation-now-supports-additional-queuing/",
        "Services": [
            "AWS Systems Manager"
        ]
    },
    {
        "Category": "Management & Governance",
        "Title": "Use AWS Config Rules to Automatically Remediate Non-compliant Resources",
        "Date": "05/09/2019",
        "Link": "https://aws.amazon.com/about-aws/whats-new/2019/09/use-aws-config-rules-to-automatically-remediate-non-compliant-resources/",
        "Services": [
            "AWS Config"
        ]
    },
    {
        "Category": "Management & Governance",
        "Title": "Container monitoring for Amazon ECS, EKS, and Kubernetes is now available in Amazon CloudWatch",
        "Date": "31/08/2019",
        "Link": "https://aws.amazon.com/about-aws/whats-new/2019/08/container-monitoring-for-amazon-ecs-eks-and-kubernetes-is-now-available-in-amazon-cloudwatch/",
        "Services": [
            "Amazon CloudWatch"
        ]
    },
    {
        "Category": "Management & Governance",
        "Title": "AWS Managed Services is Now Available in US East (Ohio), Asia Pacific (Mumbai), Asia Pacific (Seoul), Canada (Central), South America (S\u00e3o Paulo), and US West (N. California) Regions",
        "Date": "28/08/2019",
        "Link": "https://aws.amazon.com/about-aws/whats-new/2019/08/aws-managed-services-available-in-us-east-asia-pacific-canada-south-america-us-west-regions/",
        "Services": []
    },
    {
        "Category": "Management & Governance",
        "Title": "AWS Systems Manager Parameter Store announces intelligent-tiering to enable automatic parameter tier selection",
        "Date": "27/08/2019",
        "Link": "https://aws.amazon.com/about-aws/whats-new/2019/08/aws-systems-manager-parameter-store-announces-intelligent-tiering-to-enable-automatic-parameter-tier-selection/",
        "Services": [
            "AWS Systems Manager"
        ]
    },
    {
        "Category": "Management & Governance",
        "Title": "AWS Systems Manager Distributor is Now Available in AWS China (Beijing) Region, Operated by Sinnet and AWS China (Ningxia) Region, Operated by NWCD",
        "Date": "27/08/2019",
        "Link": "https://aws.amazon.com/about-aws/whats-new/2019/08/aws-systems-manager-distributor-now-available-aws-china-beijing-sinnet-ningxia-nwcd/",
        "Services": [
            "AWS Systems Manager"
        ]
    },
    {
        "Category": "Management & Governance",
        "Title": "AWS Systems Manager Advanced Instances are now available in AWS China(Beijing) Region, operated by Sinnet and AWS China (Ningxia) Region, operated by NWCD",
        "Date": "27/08/2019",
        "Link": "https://aws.amazon.com/about-aws/whats-new/2019/08/aws-systems-manager-advanced-instances-now-available-aws-china-beijing-sinnet-ningxia-nwcd/",
        "Services": [
            "AWS Systems Manager"
        ]
    },
    {
        "Category": "Management & Governance",
        "Title": "AWS Systems Manager Parameter Store features are now available in AWS China (Beijing) Region, operated by Sinnet and AWS China (Ningxia) Region, operated by NWCD",
        "Date": "23/08/2019",
        "Link": "https://aws.amazon.com/about-aws/whats-new/2019/08/aws-systems-manager-parameter-store-features-now-available-aws-china/",
        "Services": [
            "AWS Systems Manager"
        ]
    },
    {
        "Category": "Management & Governance",
        "Title": "AWS License Manager is now available in the Middle East (Bahrain) Region",
        "Date": "08/08/2019",
        "Link": "https://aws.amazon.com/about-aws/whats-new/2019/08/aws-license-manager-now-available-middle-east-bahrain-region/",
        "Services": [
            "AWS License Manager"
        ]
    },
    {
        "Category": "Management & Governance",
        "Title": "AWS CloudFormation now supports higher StackSets limits",
        "Date": "02/08/2019",
        "Link": "https://aws.amazon.com/about-aws/whats-new/2019/08/aws-cloudformation-now-supports-higher-stacksets-limits/",
        "Services": [
            "AWS CloudFormation"
        ]
    },
    {
        "Category": "Management & Governance",
        "Title": "Introducing AWS Chatbot (beta): ChatOps for AWS in Amazon Chime and Slack Chat Rooms",
        "Date": "25/07/2019",
        "Link": "https://aws.amazon.com/about-aws/whats-new/2019/07/introducing-aws-chatbot-chatops-for-aws/",
        "Services": [
            "AWS Chatbot",
            "Amazon Chime"
        ]
    },
    {
        "Category": "Management & Governance",
        "Title": "AWS Well-Architected Tool is now available in AWS Europe (London) region",
        "Date": "25/07/2019",
        "Link": "https://aws.amazon.com/about-aws/whats-new/2019/07/aws-well-architected-tool-available-aws-europe-region/",
        "Services": [
            "AWS Well-Architected Tool"
        ]
    },
    {
        "Category": "Management & Governance",
        "Title": "AWS License Manager is now available in the Asia Pacific (Hong Kong) Region",
        "Date": "10/07/2019",
        "Link": "https://aws.amazon.com/about-aws/whats-new/2019/07/aws-license-manager-now-available-asia-pacific-hong-kong-region/",
        "Services": [
            "AWS License Manager"
        ]
    },
    {
        "Category": "Management & Governance",
        "Title": "Introducing Amazon CloudWatch Anomaly Detection \u2013 Now in Preview",
        "Date": "09/07/2019",
        "Link": "https://aws.amazon.com/about-aws/whats-new/2019/07/introducing-amazon-cloudwatch-anomaly-detection-now-in-preview/",
        "Services": [
            "Amazon CloudWatch"
        ]
    },
    {
        "Category": "Management & Governance",
        "Title": "Amazon CloudWatch Events Now Supports Amazon CloudWatch Logs as a Target and Tagging of CloudWatch Events Rules",
        "Date": "27/06/2019",
        "Link": "https://aws.amazon.com/about-aws/whats-new/2019/06/amazon-cloudwatch-events-now-supports-amazon-cloudwatch-logs-target-tagging-cloudwatch-events-rules/",
        "Services": [
            "Amazon CloudWatch"
        ]
    },
    {
        "Category": "Management & Governance",
        "Title": "AWS License Manager is now available in AWS China (Beijing) region operated by Sinnet and AWS China (Ningxia) region operated by NWCD",
        "Date": "26/06/2019",
        "Link": "https://aws.amazon.com/about-aws/whats-new/2019/06/aws-license-manager-available-aws-china-beijing-sinnet-ningxia-nwcd/",
        "Services": [
            "AWS License Manager"
        ]
    },
    {
        "Category": "Management & Governance",
        "Title": "Amazon CloudWatch Adds Visibility for your .NET and SQL Server Application Health",
        "Date": "26/06/2019",
        "Link": "https://aws.amazon.com/about-aws/whats-new/2019/06/amazon-cloudwatch-adds-visibility-for-your-net-sql-server-application-health/",
        "Services": [
            "Amazon CloudWatch"
        ]
    },
    {
        "Category": "Management & Governance",
        "Title": "AWS Control Tower is now generally available",
        "Date": "24/06/2019",
        "Link": "https://aws.amazon.com/about-aws/whats-new/2019/06/aws-control-tower-is-now-generally-available/",
        "Services": [
            "AWS Control Tower"
        ]
    },
    {
        "Category": "Management & Governance",
        "Title": "Introducing Service Quotas: View and manage your quotas for AWS services from one central location",
        "Date": "24/06/2019",
        "Link": "https://aws.amazon.com/about-aws/whats-new/2019/06/introducing-service-quotas-view-and-manage-quotas-for-aws-services-from-one-location/",
        "Services": []
    },
    {
        "Category": "Management & Governance",
        "Title": "Introducing AWS Systems Manager OpsCenter to enable faster issue resolution",
        "Date": "07/06/2019",
        "Link": "https://aws.amazon.com/about-aws/whats-new/2019/06/introducing-aws-systems-manager-opscenter-to-enable-faster-issue-resolution/",
        "Services": [
            "AWS Systems Manager"
        ]
    },
    {
        "Category": "Management & Governance",
        "Title": "AWS Well-Architected Tool Now Supports 8x More Text in the Notes Field",
        "Date": "06/06/2019",
        "Link": "https://aws.amazon.com/about-aws/whats-new/2019/06/aws-well-architected-tool-now-supports-8x-more-text-in-notes-field/",
        "Services": [
            "AWS Well-Architected Tool"
        ]
    },
    {
        "Category": "Management & Governance",
        "Title": "Announcing Tag-Based Access Control for AWS CloudFormation",
        "Date": "31/05/2019",
        "Link": "https://aws.amazon.com/about-aws/whats-new/2019/05/announcing-tag-based-access-control-for-aws-cloudformation/",
        "Services": [
            "AWS CloudFormation"
        ]
    },
    {
        "Category": "Management & Governance",
        "Title": "AWS Backup Now Supports AWS CloudFormation",
        "Date": "24/05/2019",
        "Link": "https://aws.amazon.com/about-aws/whats-new/2019/05/aws-backup-now-supports-aws-cloudformation/",
        "Services": [
            "AWS Backup",
            "AWS CloudFormation"
        ]
    },
    {
        "Category": "Management & Governance",
        "Title": "AWS License Manager is Now Available in Additional Regions",
        "Date": "16/05/2019",
        "Link": "https://aws.amazon.com/about-aws/whats-new/2019/05/aws_license_manager_is_now_available_in_additional_regions/",
        "Services": [
            "AWS License Manager"
        ]
    },
    {
        "Category": "Management & Governance",
        "Title": "AWS Service Catalog Connector for ServiceNow supports CloudFormation StackSets",
        "Date": "08/05/2019",
        "Link": "https://aws.amazon.com/about-aws/whats-new/2019/05/service-catalog-servicenow-connector-now-supports-stacksets/",
        "Services": [
            "Service Catalog"
        ]
    },
    {
        "Category": "Management & Governance",
        "Title": "AWS Well-Architected Tool is now available in AWS Asia Pacific (Sydney) region",
        "Date": "30/04/2019",
        "Link": "https://aws.amazon.com/about-aws/whats-new/2019/04/aws-well-architected-tool-is-now-available-in-aws-asia-pacific-sydney-region/",
        "Services": [
            "AWS Well-Architected Tool"
        ]
    },
    {
        "Category": "Management & Governance",
        "Title": "AWS License Manager is now available in GovCloud (US) Regions",
        "Date": "19/04/2019",
        "Link": "https://aws.amazon.com/about-aws/whats-new/2019/04/awslicense_manager_govcloud_available/",
        "Services": [
            "AWS License Manager"
        ]
    },
    {
        "Category": "Management & Governance",
        "Title": "AWS Organizations now available in the AWS GovCloud (US) Regions",
        "Date": "18/04/2019",
        "Link": "https://aws.amazon.com/about-aws/whats-new/2019/04/aws_organizations_now_available_in_the_govcloud_regions/",
        "Services": [
            "AWS Organizations"
        ]
    },
    {
        "Category": "Management & Governance",
        "Title": "AWS License Manager enhances support for tracking instances on premises",
        "Date": "09/03/2019",
        "Link": "https://aws.amazon.com/about-aws/whats-new/2019/03/LicenseManagerOnPremises/",
        "Services": [
            "AWS License Manager"
        ]
    },
    {
        "Category": "Management & Governance",
        "Title": "AWS License Manager adds new capabilities to track on premises usage, number of instances, and vCPUs based on Optimize CPU settings",
        "Date": "09/03/2019",
        "Link": "https://aws.amazon.com/about-aws/whats-new/2019/02/NewLicenseManagervCPU/",
        "Services": [
            "AWS License Manager"
        ]
    },
    {
        "Category": "Management & Governance",
        "Title": "AWS Well-Architected Tool now supports architecture reviews for On Premises and Hybrid Cloud workloads",
        "Date": "19/02/2019",
        "Link": "https://aws.amazon.com/about-aws/whats-new/2019/02/aws-well-architected-tool-now-supports-architecture-reviews-for-/",
        "Services": [
            "AWS Well-Architected Tool"
        ]
    },
    {
        "Category": "Management & Governance",
        "Title": "Introducing AWS Solutions",
        "Date": "13/02/2019",
        "Link": "https://aws.amazon.com/about-aws/whats-new/2019/02/introducing-aws-solutions/",
        "Services": []
    }
]