[
    {
        "Category": "Business Applications",
        "Title": "Amazon Connect forecasting, capacity planning, and scheduling is now available in AWS GovCloud (US-West)",
        "Date": "07/02/2025",
        "Link": "https://aws.amazon.com/about-aws/whats-new/2025/07/amazon-connect-forecasting-capacity-planning-scheduling-aws-govcloud-us-west"
    },
    {
        "Category": "Business Applications",
        "Title": "Q-Index now supports seamless application-level authentication",
        "Date": "07/02/2025",
        "Link": "https://aws.amazon.com/about-aws/whats-new/2025/07/q-index-seamless-application-level-authentication/"
    },
    {
        "Category": "Business Applications",
        "Title": "Amazon Simple Email Service is now available in three new AWS Regions",
        "Date": "07/01/2025",
        "Link": "https://aws.amazon.com/about-aws/whats-new/2025/06/amazon-simple-email-service-new-aws-regions"
    },
    {
        "Category": "Business Applications",
        "Title": "AWS End User Messaging now supports Service Quotas",
        "Date": "06/24/2025",
        "Link": "https://aws.amazon.com/about-aws/whats-new/2025/06/aws-end-user-messaging-service-quotas/"
    },
    {
        "Category": "Business Applications",
        "Title": "AWS Payment Cryptography is now available in AWS Asia Pacific (Mumbai) and Asia Pacific (Osaka)",
        "Date": "06/19/2025",
        "Link": "https://aws.amazon.com/about-aws/whats-new/2025/06/aws-payment-cryptography-aws-asia-pacific-mumbai-osaka"
    },
    {
        "Category": "Business Applications",
        "Title": "Amazon Connect enhances communication limits for Outbound Campaigns",
        "Date": "06/14/2025",
        "Link": "https://aws.amazon.com/about-aws/whats-new/2025/06/amazon-connect-communication-limits-outbound-campaigns"
    },
    {
        "Category": "Business Applications",
        "Title": "Amazon Connect launches profile explorer for unified customer views",
        "Date": "06/10/2025",
        "Link": "https://aws.amazon.com/about-aws/whats-new/2025/06/amazon-connect-profile-explorer-unified-customer-views"
    },
    {
        "Category": "Business Applications",
        "Title": "AWS Wickr announces a Preview experience for files",
        "Date": "06/06/2025",
        "Link": "https://aws.amazon.com/about-aws/whats-new/2025/06/aws-wickr-preview-experience-files"
    },
    {
        "Category": "Business Applications",
        "Title": "SES Mail Manager adds Debug Logging for traffic policies",
        "Date": "05/16/2025",
        "Link": "https://aws.amazon.com/about-aws/whats-new/2025/05/ses-mail-manager-debug-logging-traffic-policies"
    },
    {
        "Category": "Business Applications",
        "Title": "Amazon Connect external voice pricing changes",
        "Date": "05/09/2025",
        "Link": "https://aws.amazon.com/about-aws/whats-new/2025/05/amazon-connect-external-voice-pricing-changes"
    },
    {
        "Category": "Business Applications",
        "Title": "Amazon Connect Contact Lens real-time dashboards are now available in AWS GovCloud (US-West)",
        "Date": "05/06/2025",
        "Link": "https://aws.amazon.com/about-aws/whats-new/2025/05/amazon-connect-contact-lens-real-time-dashboards-aws-govcloud-us-west"
    },
    {
        "Category": "Business Applications",
        "Title": "Amazon SES now supports IPv6 when calling SES outbound endpoints",
        "Date": "05/06/2025",
        "Link": "https://aws.amazon.com/about-aws/whats-new/2025/05/amazon-ses-ipv6-calling-ses-outbound-endpoints"
    },
    {
        "Category": "Business Applications",
        "Title": "Amazon Connect Contact Lens launches new real-time adherence dashboard",
        "Date": "05/02/2025",
        "Link": "https://aws.amazon.com/about-aws/whats-new/2025/05/amazon-connect-contact-lens-real-time-adherence-dashboard"
    },
    {
        "Category": "Business Applications",
        "Title": "Amazon Connect launches administrator access for agent schedules",
        "Date": "05/01/2025",
        "Link": "https://aws.amazon.com/about-aws/whats-new/2025/04/amazon-connect-administrator-access-agent-schedules"
    },
    {
        "Category": "Business Applications",
        "Title": "Amazon SES Mail Manager now supports Publish to Amazon SNS Topic Rule Action",
        "Date": "05/01/2025",
        "Link": "https://aws.amazon.com/about-aws/whats-new/2025/04/amazon-ses-mail-manager-publish-amazon-sns-topic-rule-action"
    },
    {
        "Category": "Business Applications",
        "Title": "Amazon Connect now provides bulk removal of agent schedules",
        "Date": "05/01/2025",
        "Link": "https://aws.amazon.com/about-aws/whats-new/2025/04/amazon-connect-bulk-removal-agent-schedules"
    },
    {
        "Category": "Business Applications",
        "Title": "Amazon Connect Cases adds support for managing service level agreements on cases",
        "Date": "04/18/2025",
        "Link": "https://aws.amazon.com/about-aws/whats-new/2025/04/amazon-connect-cases-managing-service-level-agreements-cases"
    },
    {
        "Category": "Business Applications",
        "Title": "Amazon SES now supports logging email sending events through AWS CloudTrail",
        "Date": "04/15/2025",
        "Link": "https://aws.amazon.com/about-aws/whats-new/2025/04/amazon-ses-logging-email-sending-events-aws-cloudtrail"
    },
    {
        "Category": "Business Applications",
        "Title": "IAM Identity Center releases new SDK plugin to streamline token exchange with an external Identity Provider",
        "Date": "04/11/2025",
        "Link": "https://aws.amazon.com/about-aws/whats-new/2025/04/iam-identity-center-sdk-plugin-streamline-token-exchange-external-identity-provider"
    },
    {
        "Category": "Business Applications",
        "Title": "AWS End User Messaging now supports IPv6",
        "Date": "04/08/2025",
        "Link": "https://aws.amazon.com/about-aws/whats-new/2025/04/aws-end-user-messaging-ipv6/"
    },
    {
        "Category": "Business Applications",
        "Title": "SES Mail Manager now supports incoming connections from customer VPCs via PrivateLink",
        "Date": "04/04/2025",
        "Link": "https://aws.amazon.com/about-aws/whats-new/2025/04/ses-mail-manager-incoming-connections-customer-vpcs-privatelink"
    },
    {
        "Category": "Business Applications",
        "Title": "Monitor service dependencies with Amazon CloudWatch Application Signals SLOs",
        "Date": "04/03/2025",
        "Link": "https://aws.amazon.com/about-aws/whats-new/2025/04/service-dependencies-amazon-cloudwatch-application-signals-slos"
    },
    {
        "Category": "Business Applications",
        "Title": "AWS Payment Cryptography launches support for exchanging cryptographic keys using ECDH",
        "Date": "04/02/2025",
        "Link": "https://aws.amazon.com/about-aws/whats-new/2025/04/aws-payment-cryptographic-keys-ecdh/"
    },
    {
        "Category": "Business Applications",
        "Title": "Amazon Connect Contact Lens now supports conversational analytics in 34 new languages",
        "Date": "04/01/2025",
        "Link": "https://aws.amazon.com/about-aws/whats-new/2025/03/amazon-connect-contact-lens-conversational-analytics-new-languages"
    },
    {
        "Category": "Business Applications",
        "Title": "Announcing 3 new features on Connected Mobility Solution on AWS",
        "Date": "03/28/2025",
        "Link": "https://aws.amazon.com/about-aws/whats-new/2025/03/3-new-features-connected-mobility-solution/"
    },
    {
        "Category": "Business Applications",
        "Title": "Amazon Connect Contact Lens now enables you to capture agent acknowledgements of performance evaluations",
        "Date": "03/22/2025",
        "Link": "https://aws.amazon.com/about-aws/whats-new/2025/03/amazon-connect-contact-lens-agents-acknowledgements-performance-evaluations"
    },
    {
        "Category": "Business Applications",
        "Title": "AWS announces the next generation of Amazon Connect where powerful AI improves every customer interaction",
        "Date": "03/19/2025",
        "Link": "https://aws.amazon.com/about-aws/whats-new/2025/03/next-generation-amazon-connect-ai-improves-customer-interaction"
    },
    {
        "Category": "Business Applications",
        "Title": "AWS announces new upgrades to the Amazon Q Business browser extension",
        "Date": "03/18/2025",
        "Link": "https://aws.amazon.com/about-aws/whats-new/2025/03/upgrades-amazon-q-business-browser-extension"
    },
    {
        "Category": "Business Applications",
        "Title": "Announcing the New AWS Wickr Admin Console",
        "Date": "03/15/2025",
        "Link": "https://aws.amazon.com/about-aws/whats-new/2025/03/new-aws-wickr-admin-console"
    },
    {
        "Category": "Business Applications",
        "Title": "Amazon Connect, Amazon WorkSpaces, and Amazon AppStream 2.0 are now Chrome Enterprise Recommended",
        "Date": "03/06/2025",
        "Link": "https://aws.amazon.com/about-aws/whats-new/2025/03/amazon-connect-workspaces-appstream-2-0-chrome-enterprise-recommended"
    },
    {
        "Category": "Business Applications",
        "Title": "Amazon Connect outbound campaigns now supports Brazil",
        "Date": "03/04/2025",
        "Link": "https://aws.amazon.com/about-aws/whats-new/2025/03/amazon-connect-outbound-campaigns-brazil"
    },
    {
        "Category": "Business Applications",
        "Title": "Amazon Connect launches the ability for agents to exchange shifts with each other",
        "Date": "03/01/2025",
        "Link": "https://aws.amazon.com/about-aws/whats-new/2025/02/amazon-connect-agents-exchange-shifts"
    },
    {
        "Category": "Business Applications",
        "Title": "Amazon Connect Contact Lens now offers AI-powered contact categorization in five new regions",
        "Date": "03/01/2025",
        "Link": "https://aws.amazon.com/about-aws/whats-new/2025/02/amazon-connect-contact-lens-ai-powered-contact-categorization-new-regions"
    },
    {
        "Category": "Business Applications",
        "Title": "AWS announces Microsoft 365 for Word and Outlook integrations for Amazon Q Business",
        "Date": "03/01/2025",
        "Link": "https://aws.amazon.com/about-aws/whats-new/2025/02/microsoft-365-word-outlook-amazon-q-business/"
    },
    {
        "Category": "Business Applications",
        "Title": "Monitor and observe apps across multiple accounts with Application Signals",
        "Date": "02/28/2025",
        "Link": "https://aws.amazon.com/about-aws/whats-new/2025/02/monitor-observe-apps-across-multiple-accounts-application-signals"
    },
    {
        "Category": "Business Applications",
        "Title": "SES Outbound now delivers to Mail Manager Archives",
        "Date": "02/20/2025",
        "Link": "https://aws.amazon.com/about-aws/whats-new/2025/02/ses-outbound-delivers-mail-manager-archives"
    },
    {
        "Category": "Business Applications",
        "Title": "Amazon SES now offers tiered pricing for Virtual Deliverability Manager",
        "Date": "02/15/2025",
        "Link": "https://aws.amazon.com/about-aws/whats-new/2025/02/amazon-ses-tiered-pricing-virtual-deliverability-manager"
    },
    {
        "Category": "Business Applications",
        "Title": "Amazon Connect Contact Lens can now take automated actions based on hold times and agent interaction time",
        "Date": "02/12/2025",
        "Link": "https://aws.amazon.com/about-aws/whats-new/2025/02/amazon-connect-contact-lens-automated-actions-based-hold-times-agent-interaction-time"
    },
    {
        "Category": "Business Applications",
        "Title": "Amazon Q Business introduces orchestration for user query management",
        "Date": "02/06/2025",
        "Link": "https://aws.amazon.com/about-aws/whats-new/2025/02/amazon-q-business-orchestration-user-query-management"
    },
    {
        "Category": "Business Applications",
        "Title": "AWS Wickr now provides a dedicated space to organize and access files",
        "Date": "02/06/2025",
        "Link": "https://aws.amazon.com/about-aws/whats-new/2025/02/aws-wickr-dedicated-space-organize-access-files"
    },
    {
        "Category": "Business Applications",
        "Title": "Amazon Connect Contact Lens can now automatically email agents about completed performance evaluations",
        "Date": "02/05/2025",
        "Link": "https://aws.amazon.com/about-aws/whats-new/2025/02/amazon-connect-contact-lens-automatically-email-agents-completed-performance-evaluations"
    },
    {
        "Category": "Business Applications",
        "Title": "Amazon Connect now supports agent time off scheduling up to 24 months in the future",
        "Date": "02/01/2025",
        "Link": "https://aws.amazon.com/about-aws/whats-new/2025/01/amazon-connect-agent-time-off-scheduling-24-months-future"
    },
    {
        "Category": "Business Applications",
        "Title": "SES Mail Manager is now available in 11 new AWS Regions, 17 total",
        "Date": "01/31/2025",
        "Link": "https://aws.amazon.com/about-aws/whats-new/2025/01/ses-mail-manager-available-new-regions"
    },
    {
        "Category": "Business Applications",
        "Title": "SES Mail Manager adds support for address and domain lists",
        "Date": "01/31/2025",
        "Link": "https://aws.amazon.com/about-aws/whats-new/2025/01/ses-mail-manager-address-domain-lists"
    },
    {
        "Category": "Business Applications",
        "Title": "Amazon Connect agent workspace now supports audio optimization for Citrix and Amazon WorkSpaces virtual desktops",
        "Date": "01/22/2025",
        "Link": "https://aws.amazon.com/about-aws/whats-new/2025/01/amazon-connect-agent-workspace-audio-optimization-citrix-workspaces-virtual-desktops"
    },
    {
        "Category": "Business Applications",
        "Title": "Amazon Connect Contact Lens launches agent performance evaluations for email contacts",
        "Date": "01/11/2025",
        "Link": "https://aws.amazon.com/about-aws/whats-new/2025/01/amazon-connect-contact-lens-agent-performance-evaluations-email-contacts"
    },
    {
        "Category": "Business Applications",
        "Title": "Amazon Connect Contact Lens now provides free trials for conversational analytics and performance evaluations",
        "Date": "01/09/2025",
        "Link": "https://aws.amazon.com/about-aws/whats-new/2025/01/amazon-connect-contact-lens-free-trials-conversational-analytics-performance-evaluations"
    }
]