[
    {
        "Category": "Compute",
        "Title": "AWS Elastic Beanstalk now supports retrieving secrets and configuration from AWS Secrets Manager and AWS Systems Manager",
        "Date": "01/04/2025",
        "Link": "https://aws.amazon.com/about-aws/whats-new/2025/03/aws-elastic-beanstalk-retrieving-secrets-configuration-secrets-manager-systems-manager",
        "Services": [
            "AWS Elastic Beanstalk",
            "AWS Secrets Manager",
            "AWS Systems Manager"
        ]
    },
    {
        "Category": "Compute",
        "Title": "Amazon EC2 R8g instances now available in AWS GovCloud (US-West)",
        "Date": "01/04/2025",
        "Link": "https://aws.amazon.com/about-aws/whats-new/2025/03/amazon-ec2-r8g-instances-govcloud-us-west/",
        "Services": [
            "Amazon EC2"
        ]
    },
    {
        "Category": "Compute",
        "Title": "Asset level capacity management for AWS Outposts",
        "Date": "01/04/2025",
        "Link": "https://aws.amazon.com/about-aws/whats-new/2025/03/asset-level-capacity-management-aws-outposts",
        "Services": [
            "AWS Outposts"
        ]
    },
    {
        "Category": "Compute",
        "Title": "Announcing the Developer Preview for AWS IoT Device SDK for Swift",
        "Date": "01/04/2025",
        "Link": "https://aws.amazon.com/about-aws/whats-new/2025/03/developer-preview-aws-iot-device-sdk-swift",
        "Services": []
    },
    {
        "Category": "Compute",
        "Title": "Amazon EC2 now supports more bandwidth and jumbo frames to select destinations",
        "Date": "29/03/2025",
        "Link": "https://aws.amazon.com/about-aws/whats-new/2025/03/amazon-ec2-bandwidth-jumbo-frames",
        "Services": [
            "Amazon EC2"
        ]
    },
    {
        "Category": "Compute",
        "Title": "Amazon EC2 C8g instances now available in AWS Asia Pacific (Tokyo)",
        "Date": "29/03/2025",
        "Link": "https://aws.amazon.com/about-aws/whats-new/2025/03/amazon-ec2-c8g-asia-pacific-tokyo/",
        "Services": [
            "Amazon EC2"
        ]
    },
    {
        "Category": "Compute",
        "Title": "Amazon EC2 R8g instances now available in AWS US West (N. California)",
        "Date": "29/03/2025",
        "Link": "https://aws.amazon.com/about-aws/whats-new/2025/03/amazon-ec2-r8g-instances-us-west-n-california/",
        "Services": [
            "Amazon EC2"
        ]
    },
    {
        "Category": "Compute",
        "Title": "Amazon GameLift Servers expands instance support with next-generation EC2 instance families",
        "Date": "28/03/2025",
        "Link": "https://aws.amazon.com/about-aws/whats-new/2025/03/amazon-gamelift-servers-expands-instance-support",
        "Services": [
            "Amazon GameLift"
        ]
    },
    {
        "Category": "Compute",
        "Title": "Amazon EC2 P5en instances are now available in US East (N. Virginia) and Asia Pacific (Jakarta)",
        "Date": "28/03/2025",
        "Link": "https://aws.amazon.com/about-aws/whats-new/2025/03/amazon-ec2-p5en-instances-n-virginia-jakarta/",
        "Services": [
            "Amazon EC2"
        ]
    },
    {
        "Category": "Compute",
        "Title": "Announcing Terraform support for AWS Parallel Computing Service",
        "Date": "25/03/2025",
        "Link": "https://aws.amazon.com/about-aws/whats-new/2025/03/announcing-terraform-parallel-computing-service/",
        "Services": []
    },
    {
        "Category": "Compute",
        "Title": "Research and Engineering Studio on AWS Version 2025.03 now available",
        "Date": "21/03/2025",
        "Link": "https://aws.amazon.com/about-aws/whats-new/2025/03/research-engineering-studio-aws-version-2025-03-available",
        "Services": []
    },
    {
        "Category": "Compute",
        "Title": "Amazon EC2 M7g instances are now available in AWS Israel (Tel Aviv) Region",
        "Date": "21/03/2025",
        "Link": "https://aws.amazon.com/about-aws/whats-new/2025/03/amazon-ec2-m7g-instances-aws-israel-tel-aviv-region",
        "Services": [
            "Amazon EC2"
        ]
    },
    {
        "Category": "Compute",
        "Title": "Amazon EC2 C7g instances are now available in AWS Canada West (Calgary) Region",
        "Date": "20/03/2025",
        "Link": "https://aws.amazon.com/about-aws/whats-new/2025/03/amazon-ec2-c7g-instances-aws-canada-west-calgary-region",
        "Services": [
            "Amazon EC2"
        ]
    },
    {
        "Category": "Compute",
        "Title": "Amazon EC2 R7g instances are now available in the AWS GovCloud (US-West) Region",
        "Date": "20/03/2025",
        "Link": "https://aws.amazon.com/about-aws/whats-new/2025/03/amazon-ec2-r7g-instances-aws-govcloud-us-west-region",
        "Services": [
            "Amazon EC2"
        ]
    },
    {
        "Category": "Compute",
        "Title": "Amazon EC2 M7gd instances are now available in Middle East (UAE) Region",
        "Date": "20/03/2025",
        "Link": "https://aws.amazon.com/about-aws/whats-new/2025/03/amazon-ec2-m7gd-instances-middle-east-uae-region",
        "Services": [
            "Amazon EC2"
        ]
    },
    {
        "Category": "Compute",
        "Title": "Amazon EC2 C7i-flex and M7i-flex instances are now available in additional AWS Regions",
        "Date": "19/03/2025",
        "Link": "https://aws.amazon.com/about-aws/whats-new/2025/03/amazon-ec2-c7i-flex-m7i-flex-instances-additional-regions/",
        "Services": [
            "Amazon EC2"
        ]
    },
    {
        "Category": "Compute",
        "Title": "Introducing Amazon EC2 I8g.48xlarge instances in US East (N. Virginia) and US West (Oregon) regions",
        "Date": "14/03/2025",
        "Link": "https://aws.amazon.com/about-aws/whats-new/2025/03/amazon-ec2-i8g-48xlarge-instances-n-virginia-oregon/",
        "Services": [
            "Amazon EC2"
        ]
    },
    {
        "Category": "Compute",
        "Title": "Amazon EC2 Allowed AMIs now integrates with AWS Config",
        "Date": "12/03/2025",
        "Link": "https://aws.amazon.com/about-aws/whats-new/2025/03/amazon-ec2-allowed-amis-integrates-aws-config",
        "Services": [
            "Amazon EC2",
            "AWS Config"
        ]
    },
    {
        "Category": "Compute",
        "Title": "Amazon EC2 R7i instances are now available in an additional AWS region",
        "Date": "12/03/2025",
        "Link": "https://aws.amazon.com/about-aws/whats-new/2025/03/amazon-ec2-r7i-instances-additional-aws-region/",
        "Services": [
            "Amazon EC2"
        ]
    },
    {
        "Category": "Compute",
        "Title": "Accelerate serverless development with ready-to-use Serverless Land Patterns in Visual Studio Code",
        "Date": "12/03/2025",
        "Link": "https://aws.amazon.com/about-aws/whats-new/2025/03/ready-to-use-serverless-land-patterns-vs-code-ide/",
        "Services": []
    },
    {
        "Category": "Compute",
        "Title": "Amazon EC2 G6e instances now available in Seoul Region",
        "Date": "11/03/2025",
        "Link": "https://aws.amazon.com/about-aws/whats-new/2025/03/amazon-ec2-g6e-instances-seoul-region",
        "Services": [
            "Amazon EC2"
        ]
    },
    {
        "Category": "Compute",
        "Title": "Amazon EC2 M7a instances are now available in AWS Asia Pacific (Sydney) Region",
        "Date": "07/03/2025",
        "Link": "https://aws.amazon.com/about-aws/whats-new/2025/03/amazon-ec2-m7a-instances-sydney-region",
        "Services": [
            "Amazon EC2"
        ]
    },
    {
        "Category": "Compute",
        "Title": "Bottlerocket now supports NVIDIA Multi-Instance GPU (MIG) for Kubernetes workloads",
        "Date": "06/03/2025",
        "Link": "https://aws.amazon.com/about-aws/whats-new/2025/03/bottlerocket-nvidia-multi-instance-gpu-mig-kubernetes-workloads",
        "Services": []
    },
    {
        "Category": "Compute",
        "Title": "Amazon EKS now envelope encrypts all Kubernetes API data by default",
        "Date": "06/03/2025",
        "Link": "https://aws.amazon.com/about-aws/whats-new/2025/03/amazon-eks-envelope-encrypts-kubernetes-api-data-default",
        "Services": []
    },
    {
        "Category": "Compute",
        "Title": "Bottlerocket now supports AWS Neuron accelerated instance types",
        "Date": "06/03/2025",
        "Link": "https://aws.amazon.com/about-aws/whats-new/2025/03/bottlerocket-aws-neuron-accelerated-instance-types",
        "Services": []
    },
    {
        "Category": "Compute",
        "Title": "Amazon EC2 M8g instances now available in AWS Europe (Ireland)",
        "Date": "06/03/2025",
        "Link": "https://aws.amazon.com/about-aws/whats-new/2025/03/amazon-ec2-8g-instances-aws-europe-ireland",
        "Services": [
            "Amazon EC2"
        ]
    },
    {
        "Category": "Compute",
        "Title": "Amazon EC2 M7g instances are now available in the AWS Europe (Zurich)",
        "Date": "06/03/2025",
        "Link": "https://aws.amazon.com/about-aws/whats-new/2025/03/amazon-ec2-m7g-instances-aws-europe-zurich",
        "Services": [
            "Amazon EC2"
        ]
    },
    {
        "Category": "Compute",
        "Title": "Amazon EC2 C8g instances now available in AWS Asia Pacific (Mumbai)",
        "Date": "06/03/2025",
        "Link": "https://aws.amazon.com/about-aws/whats-new/2025/03/amazon-ec2-c8g-instances-aws-asia-pacific-mumbai",
        "Services": [
            "Amazon EC2"
        ]
    },
    {
        "Category": "Compute",
        "Title": "SageMaker Hyperpod Flexible Training Plans now supports instant start times and multiple offers",
        "Date": "05/03/2025",
        "Link": "https://aws.amazon.com/about-aws/whats-new/2025/03/sagemaker-hyperpod-flexible-training-plans-instant-start-times-multiple-offers",
        "Services": []
    },
    {
        "Category": "Compute",
        "Title": "AWS Lambda adds support for Amazon CloudWatch Logs Live Tail in VS Code IDE",
        "Date": "05/03/2025",
        "Link": "https://aws.amazon.com/about-aws/whats-new/2025/03/aws-lambda-cloudwatch-logs-live-tail-vs-code-ide/",
        "Services": [
            "Amazon CloudWatch",
            "AWS Lambda"
        ]
    },
    {
        "Category": "Compute",
        "Title": "Announcing AWS Outposts racks for high throughput, network-intensive workloads (Preview)",
        "Date": "04/03/2025",
        "Link": "https://aws.amazon.com/about-aws/whats-new/2025/03/aws-outposts-racks-throughput-network-intensive-workloads/",
        "Services": [
            "AWS Outposts"
        ]
    },
    {
        "Category": "Compute",
        "Title": "AWS Elastic Beanstalk now supports Ruby 3.4 on Amazon Linux 2023",
        "Date": "01/03/2025",
        "Link": "https://aws.amazon.com/about-aws/whats-new/2025/02/aws-elastic-beanstalk-ruby-3-4-amazon-linux-2023/",
        "Services": [
            "AWS Elastic Beanstalk",
            "Amazon Linux 2023"
        ]
    },
    {
        "Category": "Compute",
        "Title": "Amazon EC2 Fleet added support for Block Device Mapping overrides",
        "Date": "01/03/2025",
        "Link": "https://aws.amazon.com/about-aws/whats-new/2025/02/amazon-ec2-fleet-block-device-mapping-overrides/",
        "Services": [
            "Amazon EC2"
        ]
    },
    {
        "Category": "Compute",
        "Title": "AWS Elastic Beanstalk now supports Corretto 17 and 21 with Tomcat 11",
        "Date": "01/03/2025",
        "Link": "https://aws.amazon.com/about-aws/whats-new/2025/02/aws-elastic-beanstalk-corretto-17-21-tomcat-11/",
        "Services": [
            "AWS Elastic Beanstalk"
        ]
    },
    {
        "Category": "Compute",
        "Title": "Amazon EC2 announces Time-based Copy for AMIs",
        "Date": "28/02/2025",
        "Link": "https://aws.amazon.com/about-aws/whats-new/2025/02/amazon-ec2-time-based-copy-amis",
        "Services": [
            "Amazon EC2"
        ]
    },
    {
        "Category": "Compute",
        "Title": "Amazon EC2 F2 instances are now available in Asia Pacific (Sydney)",
        "Date": "28/02/2025",
        "Link": "https://aws.amazon.com/about-aws/whats-new/2025/02/amazon-ec2-f2-instances-asia-pacific-sydney/",
        "Services": [
            "Amazon EC2"
        ]
    },
    {
        "Category": "Compute",
        "Title": "AWS Batch now supports resource aware scheduling",
        "Date": "28/02/2025",
        "Link": "https://aws.amazon.com/about-aws/whats-new/2025/02/aws-batch-resource-aware-scheduling/",
        "Services": [
            "AWS Batch"
        ]
    },
    {
        "Category": "Compute",
        "Title": "Amazon EC2 M6a instances now available in AWS Europe (Paris)",
        "Date": "27/02/2025",
        "Link": "https://aws.amazon.com/about-aws/whats-new/2025/02/amazon-ec2-m6a-instances-aws-europe-paris/",
        "Services": [
            "Amazon EC2"
        ]
    },
    {
        "Category": "Compute",
        "Title": "Amazon EC2 High Memory instances now available in Europe (Zurich) region",
        "Date": "26/02/2025",
        "Link": "https://aws.amazon.com/about-aws/whats-new/2025/02/amazon-ec2-high-memory-instances-europe-zurich-region/",
        "Services": [
            "Amazon EC2"
        ]
    },
    {
        "Category": "Compute",
        "Title": "Amazon EC2 C7gd instances are now available in the AWS GovCloud (US-East) Region",
        "Date": "25/02/2025",
        "Link": "https://aws.amazon.com/about-aws/whats-new/2025/02/amazon-ec2-c7gd-instances-govcloud-us-east-region/",
        "Services": [
            "Amazon EC2"
        ]
    },
    {
        "Category": "Compute",
        "Title": "Announcing fine-grained access control via AWS Lake Formation with EMR on EKS",
        "Date": "22/02/2025",
        "Link": "https://aws.amazon.com/about-aws/whats-new/2025/02/fine-grained-control-aws-lake-formation-emr-eks/",
        "Services": [
            "AWS Lake Formation"
        ]
    },
    {
        "Category": "Compute",
        "Title": "Amazon Elastic Beanstalk now supports Windows Server 2025 and Windows Server Core 2025 environments",
        "Date": "21/02/2025",
        "Link": "https://aws.amazon.com/about-aws/whats-new/2025/02/amazon-elastic-beanstalk-windows-server-2025-core-environments/",
        "Services": []
    },
    {
        "Category": "Compute",
        "Title": "Amazon EC2 G6e instances now available in Stockholm region",
        "Date": "21/02/2025",
        "Link": "https://aws.amazon.com/about-aws/whats-new/2025/02/amazon-ec2-g6e-instances-stockholm-region/",
        "Services": [
            "Amazon EC2"
        ]
    },
    {
        "Category": "Compute",
        "Title": "Amazon ECS increases the CPU limit for ECS tasks to 192 vCPUs",
        "Date": "20/02/2025",
        "Link": "https://aws.amazon.com/about-aws/whats-new/2025/02/amazon-ecs-increases-cpu-ecs-tasks/",
        "Services": []
    },
    {
        "Category": "Compute",
        "Title": "Amazon EC2 R6a instances now available in Canada (Central)",
        "Date": "19/02/2025",
        "Link": "https://aws.amazon.com/about-aws/whats-new/2025/02/amazon-ec2-r6a-instances-canada-central",
        "Services": [
            "Amazon EC2"
        ]
    },
    {
        "Category": "Compute",
        "Title": "Amazon EC2 C7g instances are now available in the AWS Europe (Zurich) Region",
        "Date": "15/02/2025",
        "Link": "https://aws.amazon.com/about-aws/whats-new/2025/02/amazon-ec2-c7g-instances-zurich-region/",
        "Services": [
            "Amazon EC2"
        ]
    },
    {
        "Category": "Compute",
        "Title": "AWS Lambda adds application performance monitoring (APM) for Java and .NET runtimes via Application Signals",
        "Date": "15/02/2025",
        "Link": "https://aws.amazon.com/about-aws/whats-new/2025/02/aws-lambda-adds-apm-java-net-runtimes-signals/",
        "Services": [
            "AWS Lambda"
        ]
    },
    {
        "Category": "Compute",
        "Title": "Amazon EC2 Capacity Blocks for ML is now available in several new regions",
        "Date": "14/02/2025",
        "Link": "https://aws.amazon.com/about-aws/whats-new/2025/02/amazon-ec2-capacity-blocks-ml-new-regions",
        "Services": [
            "Amazon EC2"
        ]
    },
    {
        "Category": "Compute",
        "Title": "Introducing Amazon EC2 C6in instances in Chicago and New York City Local Zones",
        "Date": "14/02/2025",
        "Link": "https://aws.amazon.com/about-aws/whats-new/2025/02/amazon-ec2-c6in-instances-chicago-new-york-city-local-zones",
        "Services": [
            "Amazon EC2"
        ]
    },
    {
        "Category": "Compute",
        "Title": "Amazon EC2 M7g instances are now available in additional regions",
        "Date": "14/02/2025",
        "Link": "https://aws.amazon.com/about-aws/whats-new/2025/02/amazon-ec2-m7g-instances-additional-regions/",
        "Services": [
            "Amazon EC2"
        ]
    },
    {
        "Category": "Compute",
        "Title": "Amazon EC2 M8g instances now available in AWS Europe (London)",
        "Date": "11/02/2025",
        "Link": "https://aws.amazon.com/about-aws/whats-new/2025/02/amazon-ec2-m8g-instances-aws-europe-london",
        "Services": [
            "Amazon EC2"
        ]
    },
    {
        "Category": "Compute",
        "Title": "Amazon EC2 High Memory U7i instances are now available in Seoul (Asia Pacific) Region",
        "Date": "08/02/2025",
        "Link": "https://aws.amazon.com/about-aws/whats-new/2025/02/amazon-ec2-high-memory-u7i-instances-seoul/",
        "Services": [
            "Amazon EC2"
        ]
    },
    {
        "Category": "Compute",
        "Title": "Cost Optimization Hub supports more EC2 Auto Scaling group recommendations",
        "Date": "07/02/2025",
        "Link": "https://aws.amazon.com/about-aws/whats-new/2025/02/cost-optimization-hub-ec2-auto-scaling-group-recommendations/",
        "Services": []
    },
    {
        "Category": "Compute",
        "Title": "Amazon EC2 M6in and M6idn instances are now available in Europe (Zurich)",
        "Date": "06/02/2025",
        "Link": "https://aws.amazon.com/about-aws/whats-new/2025/02/amazon-ec2-m6in-m6idn-instances-europe-zurich",
        "Services": [
            "Amazon EC2"
        ]
    },
    {
        "Category": "Compute",
        "Title": "Announcing the general availability of Amazon EC2 F2.6xlarge, a new F2 instance size",
        "Date": "06/02/2025",
        "Link": "https://aws.amazon.com/about-aws/whats-new/2025/02/amazon-ec2-f2-6xlarge-new-f2-instance-size/",
        "Services": [
            "Amazon EC2"
        ]
    },
    {
        "Category": "Compute",
        "Title": "Amazon EC2 C6in instances are now available in Asia Pacific (Malaysia)",
        "Date": "05/02/2025",
        "Link": "https://aws.amazon.com/about-aws/whats-new/2025/02/amazon-ec2-c6in-instances-asia-pacific-malaysia",
        "Services": [
            "Amazon EC2"
        ]
    },
    {
        "Category": "Compute",
        "Title": "AWS Batch launches new features for access control and management of AWS Batch on EKS workloads",
        "Date": "04/02/2025",
        "Link": "https://aws.amazon.com/about-aws/whats-new/2025/02/aws-batch-access-control-management-batch-eks-workloads",
        "Services": [
            "AWS Batch"
        ]
    },
    {
        "Category": "Compute",
        "Title": "Amazon EC2 now supports automated recovery of Microsoft SQL Server with VSS",
        "Date": "04/02/2025",
        "Link": "https://aws.amazon.com/about-aws/whats-new/2025/02/amazon-ec2-automated-recovery-microsoft-sql-server-vss",
        "Services": [
            "Amazon EC2"
        ]
    },
    {
        "Category": "Compute",
        "Title": "AWS Elastic Beanstalk now supports Python 3.13 on Amazon Linux 2023",
        "Date": "31/01/2025",
        "Link": "https://aws.amazon.com/about-aws/whats-new/2025/01/aws-elastic-beanstalk-python-3-13-amazon-linux-2023/",
        "Services": [
            "AWS Elastic Beanstalk",
            "Amazon Linux 2023"
        ]
    },
    {
        "Category": "Compute",
        "Title": "AWS Elastic Beanstalk now supports .NET 9 on Amazon Linux 2023",
        "Date": "31/01/2025",
        "Link": "https://aws.amazon.com/about-aws/whats-new/2025/01/aws-elastic-beanstalk-net-9-amazon-linux-2023/",
        "Services": [
            "AWS Elastic Beanstalk",
            "Amazon Linux 2023"
        ]
    },
    {
        "Category": "Compute",
        "Title": "AWS Elastic Beanstalk now supports PHP 8.4 on Amazon Linux 2023",
        "Date": "31/01/2025",
        "Link": "https://aws.amazon.com/about-aws/whats-new/2025/01/aws-elastic-beanstalk-php-8-4-amazon-linux-2023/",
        "Services": [
            "AWS Elastic Beanstalk",
            "Amazon Linux 2023"
        ]
    },
    {
        "Category": "Compute",
        "Title": "Announcing new AWS Wavelength Zone in Casablanca",
        "Date": "31/01/2025",
        "Link": "https://aws.amazon.com/about-aws/whats-new/2025/01/aws-wavelength-zone-casablanca",
        "Services": [
            "AWS Wavelength"
        ]
    },
    {
        "Category": "Compute",
        "Title": "Amazon EC2 M7g instances are now available in the AWS Middle East (UAE)",
        "Date": "29/01/2025",
        "Link": "https://aws.amazon.com/about-aws/whats-new/2025/01/amazon-ec2-m7g-instances-aws-middle-east-uae",
        "Services": [
            "Amazon EC2"
        ]
    },
    {
        "Category": "Compute",
        "Title": "AWS now supports Zone Groups for Availability Zones",
        "Date": "28/01/2025",
        "Link": "https://aws.amazon.com/about-aws/whats-new/2025/01/aws-zone-groups-availability-zones/",
        "Services": []
    },
    {
        "Category": "Compute",
        "Title": "Amazon EC2 I7ie instances now available in AWS Europe (Frankfurt, London), and Asia Pacific (Tokyo) regions",
        "Date": "25/01/2025",
        "Link": "https://aws.amazon.com/about-aws/whats-new/2025/01/amazon-ec2-i7ie-instances-frankfurt-london-tokyo-regions/",
        "Services": [
            "Amazon EC2"
        ]
    },
    {
        "Category": "Compute",
        "Title": "AWS Elastic Beanstalk improves scaling and deployment speeds for Windows instance with EC2 Fast-launch",
        "Date": "24/01/2025",
        "Link": "https://aws.amazon.com/about-aws/whats-new/2025/01/aws-elastic-beanstalk-scaling-deployment-speeds-windows-instance-ec2-fast-launch",
        "Services": [
            "AWS Elastic Beanstalk"
        ]
    },
    {
        "Category": "Compute",
        "Title": "AWS Elastic Beanstalk adds default support of EC2 Launch Template when creating new environments",
        "Date": "24/01/2025",
        "Link": "https://aws.amazon.com/about-aws/whats-new/2025/01/aws-elastic-beanstalk-ec2-launch-template-environments/",
        "Services": [
            "AWS Elastic Beanstalk"
        ]
    },
    {
        "Category": "Compute",
        "Title": "Amazon EC2 introduces provisioning control for On-Demand Capacity Reservations in the AWS GovCloud (US) Regions",
        "Date": "23/01/2025",
        "Link": "https://aws.amazon.com/about-aws/whats-new/2025/01/amazon-ec2-provisioning-on-demand-capacity-reservations/",
        "Services": [
            "Amazon EC2"
        ]
    },
    {
        "Category": "Compute",
        "Title": "Introducing new larger sizes on Amazon EC2 Flex instances",
        "Date": "17/01/2025",
        "Link": "https://aws.amazon.com/about-aws/whats-new/2025/01/amazon-ec2-flex-instances-new-larger-sizes/",
        "Services": [
            "Amazon EC2"
        ]
    },
    {
        "Category": "Compute",
        "Title": "Amazon EC2 R8g instances now available in additional regions",
        "Date": "17/01/2025",
        "Link": "https://aws.amazon.com/about-aws/whats-new/2025/01/amazon-ec2-r8g-instances-additional-regions/",
        "Services": [
            "Amazon EC2"
        ]
    },
    {
        "Category": "Compute",
        "Title": "AWS Elastic Beanstalk adds additional Spot allocation strategies",
        "Date": "16/01/2025",
        "Link": "https://aws.amazon.com/about-aws/whats-new/2025/01/aws-elastic-beanstalk-spot-allocation-strategies",
        "Services": [
            "AWS Elastic Beanstalk"
        ]
    },
    {
        "Category": "Compute",
        "Title": "Amazon EC2 C7i-flex instances are now available in the AWS GovCloud (US-West) Region",
        "Date": "16/01/2025",
        "Link": "https://aws.amazon.com/about-aws/whats-new/2025/01/amazon-ec2-c7i-flex-instances-govcloud-us-west-region/",
        "Services": [
            "Amazon EC2"
        ]
    },
    {
        "Category": "Compute",
        "Title": "EC2 Image Builder simplifies converting Windows ISO files to AMIs",
        "Date": "15/01/2025",
        "Link": "https://aws.amazon.com/about-aws/whats-new/2025/01/ec2-image-builder-converting-windows-iso-files-amis",
        "Services": []
    },
    {
        "Category": "Compute",
        "Title": "Amazon EC2 M8g instances now available in AWS Europe (Stockholm)",
        "Date": "15/01/2025",
        "Link": "https://aws.amazon.com/about-aws/whats-new/2025/01/amazon-ec2-m8g-instances-europe-stockholm/",
        "Services": [
            "Amazon EC2"
        ]
    },
    {
        "Category": "Compute",
        "Title": "AWS Compute Optimizer now expands idle and rightsizing recommendations for Amazon EC2 Auto Scaling groups",
        "Date": "10/01/2025",
        "Link": "https://aws.amazon.com/about-aws/whats-new/2025/01/aws-compute-optimizer-idle-rightsizing-recommendations-amazon-ec2-auto-scaling-groups",
        "Services": [
            "Amazon EC2 Auto Scaling",
            "Amazon EC2",
            "AWS Compute Optimizer"
        ]
    },
    {
        "Category": "Compute",
        "Title": "Amazon EC2 C8g instances now available in additional regions",
        "Date": "10/01/2025",
        "Link": "https://aws.amazon.com/about-aws/whats-new/2025/01/amazon-ec2-c8g-instances-additional-regions/",
        "Services": [
            "Amazon EC2"
        ]
    },
    {
        "Category": "Compute",
        "Title": "Amazon EC2 C7i instances now available in the AWS GovCloud (US-West) Region",
        "Date": "09/01/2025",
        "Link": "https://aws.amazon.com/about-aws/whats-new/2025/01/amazon-ec2-c7i-instances-aws-govcloud-us-west-region",
        "Services": [
            "Amazon EC2"
        ]
    }
]